corpus_judge/__init__.py
corpus_judge/justice_model.py
corpus_judge/justice_name.py
corpus_judge/justice_select.py
corpus_judge/sc.yaml
corpus_judge-0.2.0.dist-info/licenses/LICENSE
corpus_judge-0.2.0.dist-info/METADATA
corpus_judge-0.2.0.dist-info/WHEEL
corpus_judge-0.2.0.dist-info/top_level.txt
corpus_judge-0.2.0.dist-info/RECORD
