Metadata-Version: 2.4
Name: corpus-judge
Version: 0.2.0
Summary: Cleaning, setting Justices
Requires-Python: >=3.13
License-File: LICENSE
Requires-Dist: pydantic>=2.11
Requires-Dist: pyyaml>=6.0.3
Requires-Dist: unidecode>=1.4
Requires-Dist: sqlite-utils>=3.38
Dynamic: license-file
